abx_plugin_ytdlp/__init__.py
abx_plugin_ytdlp/binaries.py
abx_plugin_ytdlp/config.py
abx_plugin_ytdlp/media.py
abx_plugin_ytdlp-2024.10.28.dist-info/METADATA
abx_plugin_ytdlp-2024.10.28.dist-info/WHEEL
abx_plugin_ytdlp-2024.10.28.dist-info/entry_points.txt
abx_plugin_ytdlp-2024.10.28.dist-info/RECORD
